CHANGES.rst
MANIFEST.in
README.rst
setup.py
rsbp/__init__.py
rsbp/admin.py
rsbp/app_settings.py
rsbp/ck_settings.py
rsbp/feeds.py
rsbp/forms.py
rsbp/models.py
rsbp/tests.py
rsbp/urls.py
rsbp/views.py
rsbp.egg-info/PKG-INFO
rsbp.egg-info/SOURCES.txt
rsbp.egg-info/dependency_links.txt
rsbp.egg-info/requires.txt
rsbp.egg-info/top_level.txt
rsbp.egg-info/zip-safe
rsbp/static/rsbp/css/default.css
rsbp/templates/rsbp/base.html
rsbp/templates/rsbp/image_post.html
rsbp/templates/rsbp/post.html
rsbp/templates/rsbp/post_list.html
rsbp/templates/rsbp/tag_list.html
rsbp/templates/rsbp/text_post.html
rsbp/templates/rsbp/includes/default_meta.html
rsbp/templates/rsbp/includes/footer.html
rsbp/templates/rsbp/includes/no_posts.html
rsbp/templates/rsbp/includes/post_tags.html
rsbp/templates/rsbp/includes/title.html