Metadata-Version: 1.0
Name: rsbp
Version: 0.0.1
Summary: Really Simple Blogging Platform, written in Django
Home-page: https://github.com/alex2/rsbp
Author: Alex Holmes
Author-email: alex@alex-holmes.com
License: WTFPL
Keywords: django blog
Platform: UNKNOWN
